{
  "generatedAt": "2025-12-20T05:48:03.254Z",
  "stores": [
    {
      "id": "122",
      "city": "Burlington Fairview, ON",
      "status": "committed",
      "details": "5 produits"
    },
    {
      "id": "154",
      "city": "Hamilton East, ON",
      "status": "committed",
      "details": "5 produits"
    },
    {
      "id": "129",
      "city": "Hamilton Centre, ON",
      "status": "committed",
      "details": "5 produits"
    },
    {
      "id": "278",
      "city": "Sudbury North, ON",
      "status": "committed",
      "details": "6 produits"
    },
    {
      "id": "220",
      "city": "Waterdown, ON",
      "status": "committed",
      "details": "4 produits"
    },
    {
      "id": "45",
      "city": "Hamilton Main, ON",
      "status": "committed",
      "details": "11 produits"
    },
    {
      "id": "194",
      "city": "Hamilton Mt.East, ON",
      "status": "committed",
      "details": "4 produits"
    },
    {
      "id": "445",
      "city": "Sudbury South, ON",
      "status": "committed",
      "details": "1 produits"
    }
  ],
  "failedTwice": [],
  "retriedAndSucceeded": []
}