[
  {
    "store_id": "42",
    "city": "Guelph Stone Rd, ON",
    "name": "Luge rapide H2O Spider avec direction et freins",
    "title": "Luge rapide H2O Spider avec direction et freins",
    "price": 49.98,
    "price_raw": "49,98 $",
    "liquidation": true,
    "image": "https://media-www.canadiantire.ca/product/playing/seasonal-recreation/winter-recreation/0821088/spider-snow-bike-e7a5d494-3744-4104-9151-337a07902637-jpgrendition.jpg?im=whresize&wid=200&hei=200",
    "image_url": "https://media-www.canadiantire.ca/product/playing/seasonal-recreation/winter-recreation/0821088/spider-snow-bike-e7a5d494-3744-4104-9151-337a07902637-jpgrendition.jpg?im=whresize&wid=200&hei=200",
    "url": "https://www.canadiantire.ca/fr/pdp/luge-rapide-h2o-spider-avec-direction-et-freins-0821088p.html",
    "link": "https://www.canadiantire.ca/fr/pdp/luge-rapide-h2o-spider-avec-direction-et-freins-0821088p.html",
    "product_id": null,
    "sku": "0821088",
    "sku_formatted": "082-1088-0",
    "availability": "Il n’en reste que 5 #082-1088-0",
    "badges": [
      "Liquidation◊Exclusivité"
    ],
    "discount_percent": 50.02,
    "liquidation_price": 49.98,
    "liquidation_price_raw": "49,98 $",
    "sale_price": 49.98,
    "sale_price_raw": "49,98 $",
    "regular_price": 99.99,
    "regular_price_raw": "Était±  99,99 $prix était 99,99 $",
    "price_sale_clean": "49,98",
    "price_original_clean": "99,99"
  },
  {
    "store_id": "42",
    "city": "Guelph Stone Rd, ON",
    "name": "Liquide de préparation Evans, 1 gal",
    "title": "Liquide de préparation Evans, 1 gal",
    "price": 12.93,
    "price_raw": "12,93 $",
    "liquidation": true,
    "image": "https://media-www.canadiantire.ca/product/automotive/auto-maintenance/auto-fluids/0293102/evans-prep-fluid-1gal-5e8adf31-ac7c-40e9-9306-c6aa92e46670-jpgrendition.jpg?im=whresize&wid=200&hei=200",
    "image_url": "https://media-www.canadiantire.ca/product/automotive/auto-maintenance/auto-fluids/0293102/evans-prep-fluid-1gal-5e8adf31-ac7c-40e9-9306-c6aa92e46670-jpgrendition.jpg?im=whresize&wid=200&hei=200",
    "url": "https://www.canadiantire.ca/fr/pdp/liquide-de-preparation-evans-1-gal-0293102p.html",
    "link": "https://www.canadiantire.ca/fr/pdp/liquide-de-preparation-evans-1-gal-0293102p.html",
    "product_id": null,
    "sku": "0293102",
    "sku_formatted": "029-3102-4",
    "availability": "Il n’en reste que 5 #029-3102-4",
    "badges": [
      "Liquidation◊Mieux notés"
    ],
    "discount_percent": 74.13,
    "liquidation_price": 12.93,
    "liquidation_price_raw": "12,93 $",
    "sale_price": 12.93,
    "sale_price_raw": "12,93 $",
    "regular_price": 49.99,
    "regular_price_raw": "Était±  49,99 $prix était 49,99 $",
    "price_sale_clean": "12,93",
    "price_original_clean": "49,99"
  },
  {
    "store_id": "42",
    "city": "Guelph Stone Rd, ON",
    "name": "Système d’élimination déchets de cuisine écologique Sepura",
    "title": "Système d’élimination déchets de cuisine écologique Sepura",
    "price": 29.98,
    "price_raw": "29,98 $",
    "liquidation": true,
    "image": "https://media-www.canadiantire.ca/product/fixing/plumbing/rough-plumbing/0633486/sepura-in-sink-food-waste-separator-and-collector-9742ff37-21c0-40c1-babb-e09184b6c6bc-jpgrendition.jpg?im=whresize&wid=200&hei=200",
    "image_url": "https://media-www.canadiantire.ca/product/fixing/plumbing/rough-plumbing/0633486/sepura-in-sink-food-waste-separator-and-collector-9742ff37-21c0-40c1-babb-e09184b6c6bc-jpgrendition.jpg?im=whresize&wid=200&hei=200",
    "url": "https://www.canadiantire.ca/fr/pdp/systeme-d-elimination-dechets-de-cuisine-ecologique-sepura-0633486p.html",
    "link": "https://www.canadiantire.ca/fr/pdp/systeme-d-elimination-dechets-de-cuisine-ecologique-sepura-0633486p.html",
    "product_id": null,
    "sku": "0633486",
    "sku_formatted": "063-3486-6",
    "availability": "8 En Stock#063-3486-6",
    "badges": [
      "Liquidation◊Exclusivité"
    ],
    "discount_percent": 96,
    "liquidation_price": 29.98,
    "liquidation_price_raw": "29,98 $",
    "sale_price": 29.98,
    "sale_price_raw": "29,98 $",
    "regular_price": 749.99,
    "regular_price_raw": "Était±  749,99 $prix était 749,99 $",
    "price_sale_clean": "29,98",
    "price_original_clean": "749,99"
  },
  {
    "store_id": "42",
    "city": "Guelph Stone Rd, ON",
    "name": "Flotteur/Bateau gonflable en forme de tortue à protection UV avec auvent pour bébés",
    "title": "Flotteur/Bateau gonflable en forme de tortue à protection UV avec auvent pour bébés",
    "price": 9.98,
    "price_raw": "9,98 $",
    "liquidation": true,
    "image": "https://media-www.canadiantire.ca/product/seasonal-gardening/backyard-fun/pool-fun/0813469/inflatable-baby-boat-for-pool-turtle-f0bc9ed7-704b-4d2c-986f-2c108554e973-jpgrendition.jpg?im=whresize&wid=200&hei=200",
    "image_url": "https://media-www.canadiantire.ca/product/seasonal-gardening/backyard-fun/pool-fun/0813469/inflatable-baby-boat-for-pool-turtle-f0bc9ed7-704b-4d2c-986f-2c108554e973-jpgrendition.jpg?im=whresize&wid=200&hei=200",
    "url": "https://www.canadiantire.ca/fr/pdp/flotteur-bateau-gonflable-en-forme-de-tortue-a-protection-uv-avec-auvent-pour-bebes-0813469p.html",
    "link": "https://www.canadiantire.ca/fr/pdp/flotteur-bateau-gonflable-en-forme-de-tortue-a-protection-uv-avec-auvent-pour-bebes-0813469p.html",
    "product_id": null,
    "sku": "0813469",
    "sku_formatted": "081-3469-4",
    "availability": "11 En Stock#081-3469-4",
    "badges": [
      "Liquidation◊Exclusivité"
    ],
    "discount_percent": 50.08,
    "liquidation_price": 9.98,
    "liquidation_price_raw": "9,98 $",
    "sale_price": 9.98,
    "sale_price_raw": "9,98 $",
    "regular_price": 19.99,
    "regular_price_raw": "Était±  19,99 $prix était 19,99 $",
    "price_sale_clean": "9,98",
    "price_original_clean": "19,99"
  },
  {
    "store_id": "42",
    "city": "Guelph Stone Rd, ON",
    "name": "Machine à espresso semi-automatique à un toucher avec mousseur à lait Mr. Coffee",
    "title": "Machine à espresso semi-automatique à un toucher avec mousseur à lait Mr. Coffee",
    "price": 99.93,
    "price_raw": "99,93 $",
    "liquidation": true,
    "image": "https://media-www.canadiantire.ca/product/living/kitchen/kitchen-appliances/0430385/mr-coffee-semi-automatic-espresso-machine-w-milk-frother-482b518b-cfa5-4d80-bb51-f3dc6d06036e-jpgrendition.jpg?im=whresize&wid=200&hei=200",
    "image_url": "https://media-www.canadiantire.ca/product/living/kitchen/kitchen-appliances/0430385/mr-coffee-semi-automatic-espresso-machine-w-milk-frother-482b518b-cfa5-4d80-bb51-f3dc6d06036e-jpgrendition.jpg?im=whresize&wid=200&hei=200",
    "url": "https://www.canadiantire.ca/fr/pdp/machine-a-espresso-semi-automatique-a-un-toucher-avec-mousseur-a-lait-mr-coffee-0430385p.html",
    "link": "https://www.canadiantire.ca/fr/pdp/machine-a-espresso-semi-automatique-a-un-toucher-avec-mousseur-a-lait-mr-coffee-0430385p.html",
    "product_id": null,
    "sku": "0430385",
    "sku_formatted": "043-0385-2",
    "availability": "Il n’en reste que 3 #043-0385-2",
    "badges": [
      "Liquidation◊Mieux notés"
    ],
    "discount_percent": 77.29,
    "liquidation_price": 99.93,
    "liquidation_price_raw": "99,93 $",
    "sale_price": 99.93,
    "sale_price_raw": "99,93 $",
    "regular_price": 439.99,
    "regular_price_raw": "Était±  439,99 $prix était 439,99 $",
    "price_sale_clean": "99,93",
    "price_original_clean": "439,99"
  },
  {
    "store_id": "42",
    "city": "Guelph Stone Rd, ON",
    "name": "Friteuse numérique T-fal Easy Fry XL avec panier antiadhésif, 4,4 pintes",
    "title": "Friteuse numérique T-fal Easy Fry XL avec panier antiadhésif, 4,4 pintes",
    "price": 49.98,
    "price_raw": "49,98 $",
    "liquidation": true,
    "image": "https://media-www.canadiantire.ca/product/living/kitchen/kitchen-appliances/0430944/t-fal-easy-fry-xl-digital-air-fryer-522fbded-9325-4864-be12-05fde1c3d407-jpgrendition.jpg?im=whresize&wid=200&hei=200",
    "image_url": "https://media-www.canadiantire.ca/product/living/kitchen/kitchen-appliances/0430944/t-fal-easy-fry-xl-digital-air-fryer-522fbded-9325-4864-be12-05fde1c3d407-jpgrendition.jpg?im=whresize&wid=200&hei=200",
    "url": "https://www.canadiantire.ca/fr/pdp/friteuse-numerique-t-fal-easy-fry-xl-avec-panier-antiadhesif-4-4-pintes-0430944p.html",
    "link": "https://www.canadiantire.ca/fr/pdp/friteuse-numerique-t-fal-easy-fry-xl-avec-panier-antiadhesif-4-4-pintes-0430944p.html",
    "product_id": null,
    "sku": "0430944",
    "sku_formatted": "043-0944-2",
    "availability": "Il n’en reste que 3 #043-0944-2",
    "badges": [
      "Liquidation◊Articles à succès"
    ],
    "discount_percent": 61.55,
    "liquidation_price": 49.98,
    "liquidation_price_raw": "49,98 $",
    "sale_price": 49.98,
    "sale_price_raw": "49,98 $",
    "regular_price": 129.99,
    "regular_price_raw": "Était±  129,99 $prix était 129,99 $",
    "price_sale_clean": "49,98",
    "price_original_clean": "129,99"
  },
  {
    "store_id": "42",
    "city": "Guelph Stone Rd, ON",
    "name": "ProForm 550R - Rameur avec volant d'inertie amélioré",
    "title": "ProForm 550R - Rameur avec volant d'inertie amélioré",
    "price": 269.98,
    "price_raw": "269,98 $",
    "liquidation": true,
    "image": "https://media-www.canadiantire.ca/product/playing/exercise/exercise-equipment/1841274/proform-550r-rower-80ce24da-6954-4842-ab52-4556f4577077-jpgrendition.jpg?im=whresize&wid=200&hei=200",
    "image_url": "https://media-www.canadiantire.ca/product/playing/exercise/exercise-equipment/1841274/proform-550r-rower-80ce24da-6954-4842-ab52-4556f4577077-jpgrendition.jpg?im=whresize&wid=200&hei=200",
    "url": "https://www.canadiantire.ca/fr/pdp/proform-550r-rameur-avec-volant-d-inertie-ameliore-1841274p.html",
    "link": "https://www.canadiantire.ca/fr/pdp/proform-550r-rameur-avec-volant-d-inertie-ameliore-1841274p.html",
    "product_id": null,
    "sku": "1841274",
    "sku_formatted": "184-1274-4",
    "availability": "Il n’en reste que 6 #184-1274-4",
    "badges": [
      "Liquidation◊"
    ],
    "discount_percent": 66.25,
    "liquidation_price": 269.98,
    "liquidation_price_raw": "269,98 $",
    "sale_price": 269.98,
    "sale_price_raw": "269,98 $",
    "regular_price": 799.99,
    "regular_price_raw": "Était±  799,99 $prix était 799,99 $",
    "price_sale_clean": "269,98",
    "price_original_clean": "799,99"
  },
  {
    "store_id": "42",
    "city": "Guelph Stone Rd, ON",
    "name": "Everlast Recovery 3.0 - Pistolet de massage à percussion accessoires inclus",
    "title": "Everlast Recovery 3.0 - Pistolet de massage à percussion accessoires inclus",
    "price": 59.98,
    "price_raw": "59,98 $",
    "liquidation": true,
    "image": "https://media-www.canadiantire.ca/product/playing/exercise/exercise-accessories/1841208/everlast-3-0-recovery-percussion-massage-gun-65d6fe3f-733a-4891-8e4c-3dbc4043b5de-jpgrendition.jpg?im=whresize&wid=200&hei=200",
    "image_url": "https://media-www.canadiantire.ca/product/playing/exercise/exercise-accessories/1841208/everlast-3-0-recovery-percussion-massage-gun-65d6fe3f-733a-4891-8e4c-3dbc4043b5de-jpgrendition.jpg?im=whresize&wid=200&hei=200",
    "url": "https://www.canadiantire.ca/fr/pdp/everlast-recovery-3-0-pistolet-de-massage-a-percussion-accessoires-inclus-1841208p.html",
    "link": "https://www.canadiantire.ca/fr/pdp/everlast-recovery-3-0-pistolet-de-massage-a-percussion-accessoires-inclus-1841208p.html",
    "product_id": null,
    "sku": "1841208",
    "sku_formatted": "184-1208-4",
    "availability": "Il n’en reste que 4 #184-1208-4",
    "badges": [
      "Liquidation◊Mieux notés"
    ],
    "discount_percent": 65.72,
    "liquidation_price": 59.98,
    "liquidation_price_raw": "59,98 $",
    "sale_price": 59.98,
    "sale_price_raw": "59,98 $",
    "regular_price": 174.99,
    "regular_price_raw": "Était±  174,99 $prix était 174,99 $",
    "price_sale_clean": "59,98",
    "price_original_clean": "174,99"
  },
  {
    "store_id": "42",
    "city": "Guelph Stone Rd, ON",
    "name": "Plats de cuisson en céramique empilables PADERNO Signature, rouge, formats variés, paq. 4",
    "title": "Plats de cuisson en céramique empilables PADERNO Signature, rouge, formats variés, paq. 4",
    "price": 39.98,
    "price_raw": "39,98 $",
    "liquidation": true,
    "image": "https://media-www.canadiantire.ca/product/living/kitchen/bakeware-baking-prep/1424996/paderno-signature-4-piece-ceramic-bakeware-set-878e0aa8-33ea-4013-827d-f4c64e02fd8c-jpgrendition.jpg?im=whresize&wid=200&hei=200",
    "image_url": "https://media-www.canadiantire.ca/product/living/kitchen/bakeware-baking-prep/1424996/paderno-signature-4-piece-ceramic-bakeware-set-878e0aa8-33ea-4013-827d-f4c64e02fd8c-jpgrendition.jpg?im=whresize&wid=200&hei=200",
    "url": "https://www.canadiantire.ca/fr/pdp/plats-de-cuisson-en-ceramique-empilables-paderno-signature-rouge-formats-varies-paq-4-1424996p.html",
    "link": "https://www.canadiantire.ca/fr/pdp/plats-de-cuisson-en-ceramique-empilables-paderno-signature-rouge-formats-varies-paq-4-1424996p.html",
    "product_id": null,
    "sku": "1424996",
    "sku_formatted": "142-4996-8",
    "availability": "Il n’en reste que 7 #142-4996-8",
    "badges": [
      "Liquidation◊Exclusivité"
    ],
    "discount_percent": 57.91,
    "liquidation_price": 39.98,
    "liquidation_price_raw": "39,98 $",
    "sale_price": 39.98,
    "sale_price_raw": "39,98 $",
    "regular_price": 94.99,
    "regular_price_raw": "Était±  94,99 $prix était 94,99 $",
    "price_sale_clean": "39,98",
    "price_original_clean": "94,99"
  },
  {
    "store_id": "42",
    "city": "Guelph Stone Rd, ON",
    "name": "Sucettes au chocolat Laura Secord, assorties, 25 g",
    "title": "Sucettes au chocolat Laura Secord, assorties, 25 g",
    "price": 0.99,
    "price_raw": "0,99 $",
    "liquidation": true,
    "image": "https://media-www.canadiantire.ca/product/living/food-drink/seasonal-confectionery/1515253/laura-secord-chocolate-pops-25-g-64b8e4f0-0f66-45ed-8383-735c0e9bf488-jpgrendition.jpg?im=whresize&wid=200&hei=200",
    "image_url": "https://media-www.canadiantire.ca/product/living/food-drink/seasonal-confectionery/1515253/laura-secord-chocolate-pops-25-g-64b8e4f0-0f66-45ed-8383-735c0e9bf488-jpgrendition.jpg?im=whresize&wid=200&hei=200",
    "url": "https://www.canadiantire.ca/fr/pdp/sucettes-au-chocolat-laura-secord-assorties-25-g-1515253p.html",
    "link": "https://www.canadiantire.ca/fr/pdp/sucettes-au-chocolat-laura-secord-assorties-25-g-1515253p.html",
    "product_id": null,
    "sku": "1515253",
    "sku_formatted": "151-5253-8",
    "availability": null,
    "badges": [
      "Liquidation◊Mieux notés"
    ],
    "discount_percent": 60.24,
    "liquidation_price": 0.99,
    "liquidation_price_raw": "0,99 $",
    "sale_price": 0.99,
    "sale_price_raw": "0,99 $",
    "regular_price": 2.49,
    "regular_price_raw": "Était±  2,49 $prix était 2,49 $",
    "price_sale_clean": "0,99",
    "price_original_clean": "2,49"
  },
  {
    "store_id": "42",
    "city": "Guelph Stone Rd, ON",
    "name": "Pots à épices magnétiques Trudeau en inox avec plaque murale, paq. 6",
    "title": "Pots à épices magnétiques Trudeau en inox avec plaque murale, paq. 6",
    "price": 11.93,
    "price_raw": "11,93 $",
    "liquidation": true,
    "image": "https://media-www.canadiantire.ca/product/living/kitchen/dining-and-entertaining/0424662/6-can-magnetic-spice-rack-c2ff8318-f242-45bf-97b8-45c4a5bed507-jpgrendition.jpg?im=whresize&wid=200&hei=200",
    "image_url": "https://media-www.canadiantire.ca/product/living/kitchen/dining-and-entertaining/0424662/6-can-magnetic-spice-rack-c2ff8318-f242-45bf-97b8-45c4a5bed507-jpgrendition.jpg?im=whresize&wid=200&hei=200",
    "url": "https://www.canadiantire.ca/fr/pdp/pots-a-epices-magnetiques-trudeau-en-inox-avec-plaque-murale-paq-6-0424662p.html",
    "link": "https://www.canadiantire.ca/fr/pdp/pots-a-epices-magnetiques-trudeau-en-inox-avec-plaque-murale-paq-6-0424662p.html",
    "product_id": null,
    "sku": "0424662",
    "sku_formatted": "042-4662-0",
    "availability": "Il n’en reste que 1 #042-4662-0",
    "badges": [
      "Liquidation◊Mieux notés"
    ],
    "discount_percent": 54.1,
    "liquidation_price": 11.93,
    "liquidation_price_raw": "11,93 $",
    "sale_price": 11.93,
    "sale_price_raw": "11,93 $",
    "regular_price": 25.99,
    "regular_price_raw": "Était±  25,99 $prix était 25,99 $",
    "price_sale_clean": "11,93",
    "price_original_clean": "25,99"
  },
  {
    "store_id": "42",
    "city": "Guelph Stone Rd, ON",
    "name": "Rallonge d’intérieur NOMA, calibre 16/2, 9 pi 10 po, interrupteur MARCHE/ARRÊT, 1 prise, blanc",
    "title": "Rallonge d’intérieur NOMA, calibre 16/2, 9 pi 10 po, interrupteur MARCHE/ARRÊT, 1 prise, blanc",
    "price": 6.93,
    "price_raw": "6,93 $",
    "liquidation": true,
    "image": "https://media-www.canadiantire.ca/product/fixing/electrical/power-bars-extension-cords-timers/0522499/noma-green-9-10-3m-indoor-cord-switched-16-2-1-tap-0540deaa-2132-4934-b2a9-aff8da661f82-jpgrendition.jpg?im=whresize&wid=200&hei=200",
    "image_url": "https://media-www.canadiantire.ca/product/fixing/electrical/power-bars-extension-cords-timers/0522499/noma-green-9-10-3m-indoor-cord-switched-16-2-1-tap-0540deaa-2132-4934-b2a9-aff8da661f82-jpgrendition.jpg?im=whresize&wid=200&hei=200",
    "url": "https://www.canadiantire.ca/fr/pdp/rallonge-d-interieur-noma-calibre-16-2-9-pi-10-po-interrupteur-marche-arret-1-prise-blanc-0522475p.html",
    "link": "https://www.canadiantire.ca/fr/pdp/rallonge-d-interieur-noma-calibre-16-2-9-pi-10-po-interrupteur-marche-arret-1-prise-blanc-0522475p.html",
    "product_id": null,
    "sku": "0522475",
    "sku_formatted": "052-2475",
    "availability": null,
    "badges": [
      "Liquidation◊Mieux notés"
    ],
    "discount_percent": 53.77,
    "liquidation_price": 6.93,
    "liquidation_price_raw": "6,93 $",
    "sale_price": 6.93,
    "sale_price_raw": "6,93 $",
    "regular_price": 14.99,
    "regular_price_raw": "14,99 $Était   et+ prix était à partir de 14,99 $",
    "price_sale_clean": "6,93",
    "price_original_clean": "14,99"
  },
  {
    "store_id": "42",
    "city": "Guelph Stone Rd, ON",
    "name": "Cuiller Danielson, rouge/blanc",
    "title": "Cuiller Danielson, rouge/blanc",
    "price": 3.23,
    "price_raw": "3,23 $",
    "liquidation": true,
    "image": "https://media-www.canadiantire.ca/product/playing/fishing/fishing-lures/0782144/danielson-spoon-assortment-red-white-3-pack-20ee71fd-b37e-4b9f-a1fa-14ddc0b8bbb3-jpgrendition.jpg?im=whresize&wid=200&hei=200",
    "image_url": "https://media-www.canadiantire.ca/product/playing/fishing/fishing-lures/0782144/danielson-spoon-assortment-red-white-3-pack-20ee71fd-b37e-4b9f-a1fa-14ddc0b8bbb3-jpgrendition.jpg?im=whresize&wid=200&hei=200",
    "url": "https://www.canadiantire.ca/fr/pdp/cuiller-danielson-rouge-blanc-0782144p.html",
    "link": "https://www.canadiantire.ca/fr/pdp/cuiller-danielson-rouge-blanc-0782144p.html",
    "product_id": null,
    "sku": "0782144",
    "sku_formatted": "078-2144-2",
    "availability": "Il n’en reste que 2 #078-2144-2",
    "badges": [
      "Liquidation◊Articles à succès"
    ],
    "discount_percent": 50.23,
    "liquidation_price": 3.23,
    "liquidation_price_raw": "3,23 $",
    "sale_price": 3.23,
    "sale_price_raw": "3,23 $",
    "regular_price": 6.49,
    "regular_price_raw": "Était±  6,49 $prix était 6,49 $",
    "price_sale_clean": "3,23",
    "price_original_clean": "6,49"
  },
  {
    "store_id": "42",
    "city": "Guelph Stone Rd, ON",
    "name": "Plomb pour ver",
    "title": "Plomb pour ver",
    "price": 1.73,
    "price_raw": "1,73 $",
    "liquidation": true,
    "image": "https://media-www.canadiantire.ca/product/playing/fishing/fishing-lures/0784909/danielson-sinker-worm-size-3-1-4-oz-fe6683f5-60ca-40ca-a054-84638f38a614-jpgrendition.jpg?im=whresize&wid=200&hei=200",
    "image_url": "https://media-www.canadiantire.ca/product/playing/fishing/fishing-lures/0784909/danielson-sinker-worm-size-3-1-4-oz-fe6683f5-60ca-40ca-a054-84638f38a614-jpgrendition.jpg?im=whresize&wid=200&hei=200",
    "url": "https://www.canadiantire.ca/fr/pdp/plomb-pour-ver-0784909p.html",
    "link": "https://www.canadiantire.ca/fr/pdp/plomb-pour-ver-0784909p.html",
    "product_id": null,
    "sku": "0784909",
    "sku_formatted": "078-4909",
    "availability": null,
    "badges": [
      "Liquidation◊Exclusivité"
    ],
    "discount_percent": 50.43,
    "liquidation_price": 1.73,
    "liquidation_price_raw": "1,73 $",
    "sale_price": 1.73,
    "sale_price_raw": "1,73 $",
    "regular_price": 3.49,
    "regular_price_raw": "3,49 $Était   et+ prix était à partir de 3,49 $",
    "price_sale_clean": "1,73",
    "price_original_clean": "3,49"
  },
  {
    "store_id": "42",
    "city": "Guelph Stone Rd, ON",
    "name": "Interrupteur silencieux à bascule 3 voies CA Decorator, 15 A, 120 V, aucune mise à la terre, qualité résidentielle, couleurs variées",
    "title": "Interrupteur silencieux à bascule 3 voies CA Decorator, 15 A, 120 V, aucune mise à la terre, qualité résidentielle, couleurs variées",
    "price": 1.93,
    "price_raw": "1,93 $",
    "liquidation": true,
    "image": "undefined?im=whresize&wid=200&hei=200",
    "image_url": "undefined?im=whresize&wid=200&hei=200",
    "url": "https://www.canadiantire.ca/fr/pdp/interrupteur-silencieux-a-bascule-3-voies-ca-decorator-15-a-120-v-aucune-mise-a-la-terre-qualite-residentielle-couleurs-variees-0528225p.html",
    "link": "https://www.canadiantire.ca/fr/pdp/interrupteur-silencieux-a-bascule-3-voies-ca-decorator-15-a-120-v-aucune-mise-a-la-terre-qualite-residentielle-couleurs-variees-0528225p.html",
    "product_id": null,
    "sku": "0528225",
    "sku_formatted": "052-8225",
    "availability": null,
    "badges": [
      "Liquidation◊Mieux notés"
    ],
    "discount_percent": 59.71,
    "liquidation_price": 1.93,
    "liquidation_price_raw": "1,93 $",
    "sale_price": 1.93,
    "sale_price_raw": "1,93 $",
    "regular_price": 4.79,
    "regular_price_raw": "4,79 $Était   et+ prix était à partir de 4,79 $",
    "price_sale_clean": "1,93",
    "price_original_clean": "4,79"
  },
  {
    "store_id": "42",
    "city": "Guelph Stone Rd, ON",
    "name": "Ensemble de nettoyants automobiles Armor All, paq. 16",
    "title": "Ensemble de nettoyants automobiles Armor All, paq. 16",
    "price": 8.93,
    "price_raw": "8,93 $",
    "liquidation": true,
    "image": "https://media-www.canadiantire.ca/product/automotive/car-care-accessories/auto-cleaning-chemicals/0397080/armor-all-car-wash-packs-16ct-8ed7ef02-e539-49d9-8a49-0232d41a7968-jpgrendition.jpg?im=whresize&wid=200&hei=200",
    "image_url": "https://media-www.canadiantire.ca/product/automotive/car-care-accessories/auto-cleaning-chemicals/0397080/armor-all-car-wash-packs-16ct-8ed7ef02-e539-49d9-8a49-0232d41a7968-jpgrendition.jpg?im=whresize&wid=200&hei=200",
    "url": "https://www.canadiantire.ca/fr/pdp/ensemble-de-nettoyants-automobiles-armor-all-paq-16-0397080p.html",
    "link": "https://www.canadiantire.ca/fr/pdp/ensemble-de-nettoyants-automobiles-armor-all-paq-16-0397080p.html",
    "product_id": null,
    "sku": "0397080",
    "sku_formatted": "039-7080-6",
    "availability": "Il n’en reste que 4 #039-7080-6",
    "badges": [
      "Liquidation◊Mieux notés"
    ],
    "discount_percent": 50.36,
    "liquidation_price": 8.93,
    "liquidation_price_raw": "8,93 $",
    "sale_price": 8.93,
    "sale_price_raw": "8,93 $",
    "regular_price": 17.99,
    "regular_price_raw": "Était±  17,99 $prix était 17,99 $",
    "price_sale_clean": "8,93",
    "price_original_clean": "17,99"
  },
  {
    "store_id": "42",
    "city": "Guelph Stone Rd, ON",
    "name": "Lyre de lampe Atron Electro Industries, plaqué en laiton",
    "title": "Lyre de lampe Atron Electro Industries, plaqué en laiton",
    "price": 1.93,
    "price_raw": "1,93 $",
    "liquidation": true,
    "image": "https://media-www.canadiantire.ca/product/fixing/electrical/rough-electrical/0523167/lamp-kit-harp-8--a3163a76-5b4d-4e1d-9c6d-5ad1b0385ccd-jpgrendition.jpg?im=whresize&wid=200&hei=200",
    "image_url": "https://media-www.canadiantire.ca/product/fixing/electrical/rough-electrical/0523167/lamp-kit-harp-8--a3163a76-5b4d-4e1d-9c6d-5ad1b0385ccd-jpgrendition.jpg?im=whresize&wid=200&hei=200",
    "url": "https://www.canadiantire.ca/fr/pdp/lyre-de-lampe-atron-electro-industries-plaque-en-laiton-0523167p.html",
    "link": "https://www.canadiantire.ca/fr/pdp/lyre-de-lampe-atron-electro-industries-plaque-en-laiton-0523167p.html",
    "product_id": null,
    "sku": "0523167",
    "sku_formatted": "052-3167",
    "availability": null,
    "badges": [
      "Liquidation◊Mieux notés"
    ],
    "discount_percent": 57.02,
    "liquidation_price": 1.93,
    "liquidation_price_raw": "1,93 $",
    "sale_price": 1.93,
    "sale_price_raw": "1,93 $",
    "regular_price": 4.49,
    "regular_price_raw": "4,49 $Était   et+ prix était à partir de 4,49 $",
    "price_sale_clean": "1,93",
    "price_original_clean": "4,49"
  },
  {
    "store_id": "42",
    "city": "Guelph Stone Rd, ON",
    "name": "Ampoules chandelles incandescentes transparentes à intensité variable NOMA B10, 650 lumens, 60 W, paq. 6",
    "title": "Ampoules chandelles incandescentes transparentes à intensité variable NOMA B10, 650 lumens, 60 W, paq. 6",
    "price": 2.93,
    "price_raw": "2,93 $",
    "liquidation": true,
    "image": "https://media-www.canadiantire.ca/product/fixing/electrical/light-bulbs/0528061/noma-incandescent-b10-bulb-60w-6-pack-dimmable-bd7a5d36-4287-430a-a2d6-0b954bf09072-jpgrendition.jpg?im=whresize&wid=200&hei=200",
    "image_url": "https://media-www.canadiantire.ca/product/fixing/electrical/light-bulbs/0528061/noma-incandescent-b10-bulb-60w-6-pack-dimmable-bd7a5d36-4287-430a-a2d6-0b954bf09072-jpgrendition.jpg?im=whresize&wid=200&hei=200",
    "url": "https://www.canadiantire.ca/fr/pdp/ampoules-chandelles-incandescentes-transparentes-a-intensite-variable-noma-b10-650-lumens-60-w-paq-6-0528061p.html",
    "link": "https://www.canadiantire.ca/fr/pdp/ampoules-chandelles-incandescentes-transparentes-a-intensite-variable-noma-b10-650-lumens-60-w-paq-6-0528061p.html",
    "product_id": null,
    "sku": "0528061",
    "sku_formatted": "052-8061-2",
    "availability": "Il n’en reste que 1 #052-8061-2",
    "badges": [
      "Liquidation◊Mieux notés"
    ],
    "discount_percent": 56.85,
    "liquidation_price": 2.93,
    "liquidation_price_raw": "2,93 $",
    "sale_price": 2.93,
    "sale_price_raw": "2,93 $",
    "regular_price": 6.79,
    "regular_price_raw": "Était±  6,79 $prix était 6,79 $",
    "price_sale_clean": "2,93",
    "price_original_clean": "6,79"
  },
  {
    "store_id": "42",
    "city": "Guelph Stone Rd, ON",
    "name": "Table d'appoint de canapé ronde à dessus en bois massif avec base en métal CANVAS Kelowna, 20 po",
    "title": "Table d'appoint de canapé ronde à dessus en bois massif avec base en métal CANVAS Kelowna, 20 po",
    "price": 44.93,
    "price_raw": "44,93 $",
    "liquidation": true,
    "image": "https://media-www.canadiantire.ca/product/living/home-decor/furniture/1680070/canvas-kelowna-side-table-stackable-3f85b437-c403-4438-9710-ac064f79e2e5-jpgrendition.jpg?im=whresize&wid=200&hei=200",
    "image_url": "https://media-www.canadiantire.ca/product/living/home-decor/furniture/1680070/canvas-kelowna-side-table-stackable-3f85b437-c403-4438-9710-ac064f79e2e5-jpgrendition.jpg?im=whresize&wid=200&hei=200",
    "url": "https://www.canadiantire.ca/fr/pdp/table-d-appoint-de-canape-ronde-a-dessus-en-bois-massif-avec-base-en-metal-canvas-kelowna-20-po-1680070p.html",
    "link": "https://www.canadiantire.ca/fr/pdp/table-d-appoint-de-canape-ronde-a-dessus-en-bois-massif-avec-base-en-metal-canvas-kelowna-20-po-1680070p.html",
    "product_id": null,
    "sku": "1680070",
    "sku_formatted": "168-0070-4",
    "availability": "Il n’en reste que 1 #168-0070-4",
    "badges": [
      "Liquidation◊Mieux notés"
    ],
    "discount_percent": 50.07,
    "liquidation_price": 44.93,
    "liquidation_price_raw": "44,93 $",
    "sale_price": 44.93,
    "sale_price_raw": "44,93 $",
    "regular_price": 89.99,
    "regular_price_raw": "Était±  89,99 $prix était 89,99 $",
    "price_sale_clean": "44,93",
    "price_original_clean": "89,99"
  },
  {
    "store_id": "42",
    "city": "Guelph Stone Rd, ON",
    "name": "Switft Burn - Sauce piquante, paq. 5",
    "title": "Switft Burn - Sauce piquante, paq. 5",
    "price": 9.99,
    "price_raw": "9,99 $",
    "liquidation": true,
    "image": "https://media-www.canadiantire.ca/product/living/food-drink/seasonal-confectionery/1516647/swift-burn-hot-sauces-5pk-aee9dd03-9b98-4fab-b34a-9cca27103e0d-jpgrendition.jpg?im=whresize&wid=200&hei=200",
    "image_url": "https://media-www.canadiantire.ca/product/living/food-drink/seasonal-confectionery/1516647/swift-burn-hot-sauces-5pk-aee9dd03-9b98-4fab-b34a-9cca27103e0d-jpgrendition.jpg?im=whresize&wid=200&hei=200",
    "url": "https://www.canadiantire.ca/fr/pdp/switft-burn-sauce-piquante-paq-5-1516647p.html",
    "link": "https://www.canadiantire.ca/fr/pdp/switft-burn-sauce-piquante-paq-5-1516647p.html",
    "product_id": null,
    "sku": "1516647",
    "sku_formatted": "151-6647-6",
    "availability": "Il n’en reste que 1 #151-6647-6",
    "badges": [
      "Liquidation◊"
    ],
    "discount_percent": 56.55,
    "liquidation_price": 9.99,
    "liquidation_price_raw": "9,99 $",
    "sale_price": 9.99,
    "sale_price_raw": "9,99 $",
    "regular_price": 22.99,
    "regular_price_raw": "Était±  22,99 $prix était 22,99 $",
    "price_sale_clean": "9,99",
    "price_original_clean": "22,99"
  },
  {
    "store_id": "42",
    "city": "Guelph Stone Rd, ON",
    "name": "Rail d'éclairage à 3 lampes tête réglables NOMA Osgoode, nickel brossé",
    "title": "Rail d'éclairage à 3 lampes tête réglables NOMA Osgoode, nickel brossé",
    "price": 44.93,
    "price_raw": "44,93 $",
    "liquidation": true,
    "image": "https://media-www.canadiantire.ca/product/living/home-decor/lighting/0529726/noma-3-lt-osgoode-track-light-be911878-db1b-4a20-9cfb-72ac9af3278c-jpgrendition.jpg?im=whresize&wid=200&hei=200",
    "image_url": "https://media-www.canadiantire.ca/product/living/home-decor/lighting/0529726/noma-3-lt-osgoode-track-light-be911878-db1b-4a20-9cfb-72ac9af3278c-jpgrendition.jpg?im=whresize&wid=200&hei=200",
    "url": "https://www.canadiantire.ca/fr/pdp/rail-d-eclairage-a-3-lampes-tete-reglables-noma-osgoode-nickel-brosse-0529726p.html",
    "link": "https://www.canadiantire.ca/fr/pdp/rail-d-eclairage-a-3-lampes-tete-reglables-noma-osgoode-nickel-brosse-0529726p.html",
    "product_id": null,
    "sku": "0529726",
    "sku_formatted": "052-9726-6",
    "availability": "Il n’en reste que 1 #052-9726-6",
    "badges": [
      "Liquidation◊Exclusivité"
    ],
    "discount_percent": 50.07,
    "liquidation_price": 44.93,
    "liquidation_price_raw": "44,93 $",
    "sale_price": 44.93,
    "sale_price_raw": "44,93 $",
    "regular_price": 89.99,
    "regular_price_raw": "Était±  89,99 $prix était 89,99 $",
    "price_sale_clean": "44,93",
    "price_original_clean": "89,99"
  },
  {
    "store_id": "42",
    "city": "Guelph Stone Rd, ON",
    "name": "Scie-cloche à pointe au carbure LENOX, 1 1/8 po",
    "title": "Scie-cloche à pointe au carbure LENOX, 1 1/8 po",
    "price": 9.93,
    "price_raw": "9,93 $",
    "liquidation": true,
    "image": "https://media-www.canadiantire.ca/product/fixing/tools/power-tool-accessories/0540764/lenox-carbide-tipped-hole-saw-1-1-8-29mm-b4b53a30-ff93-453f-8fd2-c72bcd68a519-jpgrendition.jpg?im=whresize&wid=200&hei=200",
    "image_url": "https://media-www.canadiantire.ca/product/fixing/tools/power-tool-accessories/0540764/lenox-carbide-tipped-hole-saw-1-1-8-29mm-b4b53a30-ff93-453f-8fd2-c72bcd68a519-jpgrendition.jpg?im=whresize&wid=200&hei=200",
    "url": "https://www.canadiantire.ca/fr/pdp/scie-cloche-a-pointe-au-carbure-lenox-1-1-8-po-0540764p.html",
    "link": "https://www.canadiantire.ca/fr/pdp/scie-cloche-a-pointe-au-carbure-lenox-1-1-8-po-0540764p.html",
    "product_id": null,
    "sku": "0540764",
    "sku_formatted": "054-0764-4",
    "availability": "Il n’en reste que 2 #054-0764-4",
    "badges": [
      "Liquidation◊Exclusivité"
    ],
    "discount_percent": 61.79,
    "liquidation_price": 9.93,
    "liquidation_price_raw": "9,93 $",
    "sale_price": 9.93,
    "sale_price_raw": "9,93 $",
    "regular_price": 25.99,
    "regular_price_raw": "Était±  25,99 $prix était 25,99 $",
    "price_sale_clean": "9,93",
    "price_original_clean": "25,99"
  },
  {
    "store_id": "42",
    "city": "Guelph Stone Rd, ON",
    "name": "Mini-quad/VTT porteur électrique Huffy Boltz 6 V, rouge/bleu, 18 mois à 3 ans",
    "title": "Mini-quad/VTT porteur électrique Huffy Boltz 6 V, rouge/bleu, 18 mois à 3 ans",
    "price": 99.98,
    "price_raw": "99,98 $",
    "liquidation": true,
    "image": "https://media-www.canadiantire.ca/product/playing/cycling/wheeled-goods/1840678/6v-boltz-electric-ride-on-66667b95-eb65-4da2-9576-fe421594655b-jpgrendition.jpg?im=whresize&wid=200&hei=200",
    "image_url": "https://media-www.canadiantire.ca/product/playing/cycling/wheeled-goods/1840678/6v-boltz-electric-ride-on-66667b95-eb65-4da2-9576-fe421594655b-jpgrendition.jpg?im=whresize&wid=200&hei=200",
    "url": "https://www.canadiantire.ca/fr/pdp/mini-quad-vtt-porteur-electrique-huffy-boltz-6-v-rouge-bleu-18-mois-a-3-ans-1840678p.html",
    "link": "https://www.canadiantire.ca/fr/pdp/mini-quad-vtt-porteur-electrique-huffy-boltz-6-v-rouge-bleu-18-mois-a-3-ans-1840678p.html",
    "product_id": null,
    "sku": "1840678",
    "sku_formatted": "184-0678-0",
    "availability": "11 En Stock#184-0678-0",
    "badges": [
      "Liquidation◊"
    ],
    "discount_percent": 54.55,
    "liquidation_price": 99.98,
    "liquidation_price_raw": "99,98 $",
    "sale_price": 99.98,
    "sale_price_raw": "99,98 $",
    "regular_price": 219.99,
    "regular_price_raw": "Était±  219,99 $prix était 219,99 $",
    "price_sale_clean": "99,98",
    "price_original_clean": "219,99"
  },
  {
    "store_id": "42",
    "city": "Guelph Stone Rd, ON",
    "name": "Décoration de chandelier Pat'Patrouille pour fête d’anniversaire/chambre, paq. 6",
    "title": "Décoration de chandelier Pat'Patrouille pour fête d’anniversaire/chambre, paq. 6",
    "price": 2.93,
    "price_raw": "2,93 $",
    "liquidation": true,
    "image": "https://media-www.partycity.ca/product/seasonal-gardening/party-city-everyday/party-city-party-supplies-decor/8423637/6ct-3d-strng-deco-paw-ptrl-adv-7159390e-c15c-4bb5-9c90-63758e9c8c3d-jpgrendition.jpg?im=whresize&wid=200&hei=200",
    "image_url": "https://media-www.partycity.ca/product/seasonal-gardening/party-city-everyday/party-city-party-supplies-decor/8423637/6ct-3d-strng-deco-paw-ptrl-adv-7159390e-c15c-4bb5-9c90-63758e9c8c3d-jpgrendition.jpg?im=whresize&wid=200&hei=200",
    "url": "https://www.canadiantire.ca/fr/pdp/decoration-de-chandelier-pat-patrouille-pour-fete-d-anniversaire-chambre-paq-6-8423637p.html",
    "link": "https://www.canadiantire.ca/fr/pdp/decoration-de-chandelier-pat-patrouille-pour-fete-d-anniversaire-chambre-paq-6-8423637p.html",
    "product_id": null,
    "sku": "8423637",
    "sku_formatted": "842-3637-4",
    "availability": "8 En Stock#842-3637-4",
    "badges": [
      "Liquidation◊Mieux notés"
    ],
    "discount_percent": 60.88,
    "liquidation_price": 2.93,
    "liquidation_price_raw": "2,93 $",
    "sale_price": 2.93,
    "sale_price_raw": "2,93 $",
    "regular_price": 7.49,
    "regular_price_raw": "Était±  7,49 $prix était 7,49 $",
    "price_sale_clean": "2,93",
    "price_original_clean": "7,49"
  },
  {
    "store_id": "42",
    "city": "Guelph Stone Rd, ON",
    "name": "Housse pour radiateur de terrasse vertical For Living avec fermeture à glissière, 34 x 34 x 89 po",
    "title": "Housse pour radiateur de terrasse vertical For Living avec fermeture à glissière, 34 x 34 x 89 po",
    "price": 6.98,
    "price_raw": "6,98 $",
    "liquidation": true,
    "image": "https://media-www.canadiantire.ca/product/seasonal-gardening/backyard-living/outdoor-heating/0853053/for-living-outdoor-patio-heater-cover-a693eef6-7315-4a60-b92d-b0adb841aa4f-jpgrendition.jpg?im=whresize&wid=200&hei=200",
    "image_url": "https://media-www.canadiantire.ca/product/seasonal-gardening/backyard-living/outdoor-heating/0853053/for-living-outdoor-patio-heater-cover-a693eef6-7315-4a60-b92d-b0adb841aa4f-jpgrendition.jpg?im=whresize&wid=200&hei=200",
    "url": "https://www.canadiantire.ca/fr/pdp/housse-pour-radiateur-de-terrasse-vertical-for-living-avec-fermeture-a-glissiere-34-x-34-x-89-po-0853053p.html",
    "link": "https://www.canadiantire.ca/fr/pdp/housse-pour-radiateur-de-terrasse-vertical-for-living-avec-fermeture-a-glissiere-34-x-34-x-89-po-0853053p.html",
    "product_id": null,
    "sku": "0853053",
    "sku_formatted": "085-3053-4",
    "availability": "47 En Stock#085-3053-4",
    "badges": [
      "Liquidation◊Mieux notés"
    ],
    "discount_percent": 65.08,
    "liquidation_price": 6.98,
    "liquidation_price_raw": "6,98 $",
    "sale_price": 6.98,
    "sale_price_raw": "6,98 $",
    "regular_price": 19.99,
    "regular_price_raw": "Était±  19,99 $prix était 19,99 $",
    "price_sale_clean": "6,98",
    "price_original_clean": "19,99"
  },
  {
    "store_id": "42",
    "city": "Guelph Stone Rd, ON",
    "name": "Plomb à fente amovible Danielson, format 3/0, paq. 40",
    "title": "Plomb à fente amovible Danielson, format 3/0, paq. 40",
    "price": 1.23,
    "price_raw": "1,23 $",
    "liquidation": true,
    "image": "https://media-www.canadiantire.ca/product/playing/fishing/fishing-lures/0784974/danielson-removable-split-shot-sinker-size-3-0-fd698e4f-1ce8-44a0-b76f-7bc91b786c8d-jpgrendition.jpg?im=whresize&wid=200&hei=200",
    "image_url": "https://media-www.canadiantire.ca/product/playing/fishing/fishing-lures/0784974/danielson-removable-split-shot-sinker-size-3-0-fd698e4f-1ce8-44a0-b76f-7bc91b786c8d-jpgrendition.jpg?im=whresize&wid=200&hei=200",
    "url": "https://www.canadiantire.ca/fr/pdp/plomb-a-fente-amovible-danielson-format-3-0-paq-40-0784974p.html",
    "link": "https://www.canadiantire.ca/fr/pdp/plomb-a-fente-amovible-danielson-format-3-0-paq-40-0784974p.html",
    "product_id": null,
    "sku": "0784974",
    "sku_formatted": "078-4974-4",
    "availability": "Il n’en reste que 1 #078-4974-4",
    "badges": [
      "Liquidation◊Mieux notés"
    ],
    "discount_percent": 50.6,
    "liquidation_price": 1.23,
    "liquidation_price_raw": "1,23 $",
    "sale_price": 1.23,
    "sale_price_raw": "1,23 $",
    "regular_price": 2.49,
    "regular_price_raw": "Était±  2,49 $prix était 2,49 $",
    "price_sale_clean": "1,23",
    "price_original_clean": "2,49"
  },
  {
    "store_id": "42",
    "city": "Guelph Stone Rd, ON",
    "name": "Adaptateur 6 voies vers 4 voies plat pour remorque REESE Towpower avec multimètre à DEL",
    "title": "Adaptateur 6 voies vers 4 voies plat pour remorque REESE Towpower avec multimètre à DEL",
    "price": 6.93,
    "price_raw": "6,93 $",
    "liquidation": true,
    "image": "https://media-www.canadiantire.ca/product/automotive/automotive-outdoor-adventure/auto-travel-storage/0406844/adapter6to4wledtester-472c624b-c367-4021-a5a3-f7a62f8854fc-jpgrendition.jpg?im=whresize&wid=200&hei=200",
    "image_url": "https://media-www.canadiantire.ca/product/automotive/automotive-outdoor-adventure/auto-travel-storage/0406844/adapter6to4wledtester-472c624b-c367-4021-a5a3-f7a62f8854fc-jpgrendition.jpg?im=whresize&wid=200&hei=200",
    "url": "https://www.canadiantire.ca/fr/pdp/adaptateur-6-voies-vers-4-voies-plat-pour-remorque-reese-towpower-avec-multimetre-a-del-0406844p.html",
    "link": "https://www.canadiantire.ca/fr/pdp/adaptateur-6-voies-vers-4-voies-plat-pour-remorque-reese-towpower-avec-multimetre-a-del-0406844p.html",
    "product_id": null,
    "sku": "0406844",
    "sku_formatted": "040-6844-0",
    "availability": "Il n’en reste que 1 #040-6844-0",
    "badges": [
      "Liquidation◊"
    ],
    "discount_percent": 76.89,
    "liquidation_price": 6.93,
    "liquidation_price_raw": "6,93 $",
    "sale_price": 6.93,
    "sale_price_raw": "6,93 $",
    "regular_price": 29.99,
    "regular_price_raw": "Était±  29,99 $prix était 29,99 $",
    "price_sale_clean": "6,93",
    "price_original_clean": "29,99"
  },
  {
    "store_id": "42",
    "city": "Guelph Stone Rd, ON",
    "name": "Piles alcalines de rechange PetSafe 6V, paq. 2",
    "title": "Piles alcalines de rechange PetSafe 6V, paq. 2",
    "price": 4.93,
    "price_raw": "4,93 $",
    "liquidation": true,
    "image": "https://media-www.canadiantire.ca/product/living/pet-care/pet-accessories/0427101/6v-battery-42-7100-02-9a422d99-f97d-4e95-9814-891456a42fba-jpgrendition.jpg?im=whresize&wid=200&hei=200",
    "image_url": "https://media-www.canadiantire.ca/product/living/pet-care/pet-accessories/0427101/6v-battery-42-7100-02-9a422d99-f97d-4e95-9814-891456a42fba-jpgrendition.jpg?im=whresize&wid=200&hei=200",
    "url": "https://www.canadiantire.ca/fr/pdp/piles-alcalines-de-rechange-petsafe-6v-paq-2-0427101p.html",
    "link": "https://www.canadiantire.ca/fr/pdp/piles-alcalines-de-rechange-petsafe-6v-paq-2-0427101p.html",
    "product_id": null,
    "sku": "0427101",
    "sku_formatted": "042-7101-8",
    "availability": "Il n’en reste que 1 #042-7101-8",
    "badges": [
      "Liquidation◊Mieux notés"
    ],
    "discount_percent": 67.11,
    "liquidation_price": 4.93,
    "liquidation_price_raw": "4,93 $",
    "sale_price": 4.93,
    "sale_price_raw": "4,93 $",
    "regular_price": 14.99,
    "regular_price_raw": "Était±  14,99 $prix était 14,99 $",
    "price_sale_clean": "4,93",
    "price_original_clean": "14,99"
  },
  {
    "store_id": "42",
    "city": "Guelph Stone Rd, ON",
    "name": "Vélo de montagne Raleigh Tracker, double suspension, roue de 27,5 po, bleu",
    "title": "Vélo de montagne Raleigh Tracker, double suspension, roue de 27,5 po, bleu",
    "price": 374.99,
    "price_raw": "374,99 $",
    "liquidation": true,
    "image": "https://media-www.canadiantire.ca/product/playing/cycling/bicycles/0711970/raleigh-tracker-men-s-dual-suspension-mountain-bike-27-5-in-c2184457-e07d-4944-9f90-69add3ef4428-jpgrendition.jpg?im=whresize&wid=200&hei=200",
    "image_url": "https://media-www.canadiantire.ca/product/playing/cycling/bicycles/0711970/raleigh-tracker-men-s-dual-suspension-mountain-bike-27-5-in-c2184457-e07d-4944-9f90-69add3ef4428-jpgrendition.jpg?im=whresize&wid=200&hei=200",
    "url": "https://www.canadiantire.ca/fr/pdp/velo-de-montagne-raleigh-tracker-double-suspension-roue-de-27-5-po-bleu-0711970p.html",
    "link": "https://www.canadiantire.ca/fr/pdp/velo-de-montagne-raleigh-tracker-double-suspension-roue-de-27-5-po-bleu-0711970p.html",
    "product_id": null,
    "sku": "0711970",
    "sku_formatted": "071-1970-4",
    "availability": "Il n’en reste que 4 #071-1970-4",
    "badges": [
      "Liquidation◊Exclusivité"
    ],
    "discount_percent": 50,
    "liquidation_price": 374.99,
    "liquidation_price_raw": "374,99 $",
    "sale_price": 374.99,
    "sale_price_raw": "374,99 $",
    "regular_price": 749.99,
    "regular_price_raw": "Était±  749,99 $prix était 749,99 $",
    "price_sale_clean": "374,99",
    "price_original_clean": "749,99"
  },
  {
    "store_id": "42",
    "city": "Guelph Stone Rd, ON",
    "name": "Pavillon de plafond de luxe Atron Electro Industries LA613, 5 po, blanc",
    "title": "Pavillon de plafond de luxe Atron Electro Industries LA613, 5 po, blanc",
    "price": 1.93,
    "price_raw": "1,93 $",
    "liquidation": true,
    "image": "https://media-www.canadiantire.ca/product/fixing/electrical/rough-electrical/0522874/canopy-kit-white-deluxe-78b0d445-2443-4068-9900-25c1295b4d17-jpgrendition.jpg?im=whresize&wid=200&hei=200",
    "image_url": "https://media-www.canadiantire.ca/product/fixing/electrical/rough-electrical/0522874/canopy-kit-white-deluxe-78b0d445-2443-4068-9900-25c1295b4d17-jpgrendition.jpg?im=whresize&wid=200&hei=200",
    "url": "https://www.canadiantire.ca/fr/pdp/pavillon-de-plafond-de-luxe-atron-electro-industries-la613-5-po-blanc-0522874p.html",
    "link": "https://www.canadiantire.ca/fr/pdp/pavillon-de-plafond-de-luxe-atron-electro-industries-la613-5-po-blanc-0522874p.html",
    "product_id": null,
    "sku": "0522874",
    "sku_formatted": "052-2874-4",
    "availability": "Il n’en reste que 1 #052-2874-4",
    "badges": [
      "Liquidation◊Mieux notés"
    ],
    "discount_percent": 67.78,
    "liquidation_price": 1.93,
    "liquidation_price_raw": "1,93 $",
    "sale_price": 1.93,
    "sale_price_raw": "1,93 $",
    "regular_price": 5.99,
    "regular_price_raw": "Était±  5,99 $prix était 5,99 $",
    "price_sale_clean": "1,93",
    "price_original_clean": "5,99"
  },
  {
    "store_id": "42",
    "city": "Guelph Stone Rd, ON",
    "name": "Boîte polyvalente The Home Edit par iDESIGN, très grand",
    "title": "Boîte polyvalente The Home Edit par iDESIGN, très grand",
    "price": 24.93,
    "price_raw": "24,93 $",
    "liquidation": true,
    "image": "https://media-www.canadiantire.ca/product/living/home-organization/storage-containers/1429618/the-home-edit-by-idesign-xl-bin-onyx-7f318ffc-cf66-49a1-b3df-4436874d2e59-jpgrendition.jpg?im=whresize&wid=200&hei=200",
    "image_url": "https://media-www.canadiantire.ca/product/living/home-organization/storage-containers/1429618/the-home-edit-by-idesign-xl-bin-onyx-7f318ffc-cf66-49a1-b3df-4436874d2e59-jpgrendition.jpg?im=whresize&wid=200&hei=200",
    "url": "https://www.canadiantire.ca/fr/pdp/boite-polyvalente-the-home-edit-par-idesign-tres-grand-1429617p.html",
    "link": "https://www.canadiantire.ca/fr/pdp/boite-polyvalente-the-home-edit-par-idesign-tres-grand-1429617p.html",
    "product_id": null,
    "sku": "1429617",
    "sku_formatted": "142-9617",
    "availability": null,
    "badges": [
      "Liquidation◊Exclusivité"
    ],
    "discount_percent": 50.13,
    "liquidation_price": 24.93,
    "liquidation_price_raw": "24,93 $",
    "sale_price": 24.93,
    "sale_price_raw": "24,93 $",
    "regular_price": 49.99,
    "regular_price_raw": "49,99 $Était   et+ prix était à partir de 49,99 $",
    "price_sale_clean": "24,93",
    "price_original_clean": "49,99"
  },
  {
    "store_id": "42",
    "city": "Guelph Stone Rd, ON",
    "name": "Plaque murale pour interrupteur à bascule en nylon Leviton PJ262-748 Decora, taille intermédiaire, 2 dispositifs, gris",
    "title": "Plaque murale pour interrupteur à bascule en nylon Leviton PJ262-748 Decora, taille intermédiaire, 2 dispositifs, gris",
    "price": 1.43,
    "price_raw": "1,43 $",
    "liquidation": true,
    "image": "https://media-www.canadiantire.ca/product/fixing/electrical/rough-electrical/0523444/decora-wallplate-2-gang-grey-midway-size-64cdd973-2450-4a32-885e-78474587a602-jpgrendition.jpg?im=whresize&wid=200&hei=200",
    "image_url": "https://media-www.canadiantire.ca/product/fixing/electrical/rough-electrical/0523444/decora-wallplate-2-gang-grey-midway-size-64cdd973-2450-4a32-885e-78474587a602-jpgrendition.jpg?im=whresize&wid=200&hei=200",
    "url": "https://www.canadiantire.ca/fr/pdp/plaque-murale-pour-interrupteur-a-bascule-en-nylon-leviton-pj262-748-decora-taille-intermediaire-2-dispositifs-gris-0523444p.html",
    "link": "https://www.canadiantire.ca/fr/pdp/plaque-murale-pour-interrupteur-a-bascule-en-nylon-leviton-pj262-748-decora-taille-intermediaire-2-dispositifs-gris-0523444p.html",
    "product_id": null,
    "sku": "0523444",
    "sku_formatted": "052-3444-2",
    "availability": "Il n’en reste que 1 #052-3444-2",
    "badges": [
      "Liquidation◊"
    ],
    "discount_percent": 64.16,
    "liquidation_price": 1.43,
    "liquidation_price_raw": "1,43 $",
    "sale_price": 1.43,
    "sale_price_raw": "1,43 $",
    "regular_price": 3.99,
    "regular_price_raw": "Était±  3,99 $prix était 3,99 $",
    "price_sale_clean": "1,43",
    "price_original_clean": "3,99"
  },
  {
    "store_id": "42",
    "city": "Guelph Stone Rd, ON",
    "name": "Éponge abrasive à double angle 3M Pro Grade, pour la précision, en oxyde d'aluminium, pour bois, métal, plastique et maçonnerie",
    "title": "Éponge abrasive à double angle 3M Pro Grade, pour la précision, en oxyde d'aluminium, pour bois, métal, plastique et maçonnerie",
    "price": 3.93,
    "price_raw": "3,93 $",
    "liquidation": true,
    "image": "https://media-www.canadiantire.ca/product/fixing/tools/power-tool-accessories/0542417/3m-angle-sanding-sponge-36-grit-e109d44e-8426-469c-9d61-33597d9e715a-jpgrendition.jpg?im=whresize&wid=200&hei=200",
    "image_url": "https://media-www.canadiantire.ca/product/fixing/tools/power-tool-accessories/0542417/3m-angle-sanding-sponge-36-grit-e109d44e-8426-469c-9d61-33597d9e715a-jpgrendition.jpg?im=whresize&wid=200&hei=200",
    "url": "https://www.canadiantire.ca/fr/pdp/eponge-abrasive-a-double-angle-3m-pro-grade-pour-la-precision-en-oxyde-d-aluminium-pour-bois-metal-plastique-et-maconnerie-0542417p.html",
    "link": "https://www.canadiantire.ca/fr/pdp/eponge-abrasive-a-double-angle-3m-pro-grade-pour-la-precision-en-oxyde-d-aluminium-pour-bois-metal-plastique-et-maconnerie-0542417p.html",
    "product_id": null,
    "sku": "0542417",
    "sku_formatted": "054-2417",
    "availability": null,
    "badges": [
      "Liquidation◊Mieux notés"
    ],
    "discount_percent": 50.81,
    "liquidation_price": 3.93,
    "liquidation_price_raw": "3,93 $",
    "sale_price": 3.93,
    "sale_price_raw": "3,93 $",
    "regular_price": 7.99,
    "regular_price_raw": "7,99 $Était   et+ prix était à partir de 7,99 $",
    "price_sale_clean": "3,93",
    "price_original_clean": "7,99"
  },
  {
    "store_id": "42",
    "city": "Guelph Stone Rd, ON",
    "name": "Plaque d'interrupteur à bascule surdimensionnée Atron Electro Industries 1037R, 1 dispositif, blanc",
    "title": "Plaque d'interrupteur à bascule surdimensionnée Atron Electro Industries 1037R, 1 dispositif, blanc",
    "price": 1.43,
    "price_raw": "1,43 $",
    "liquidation": true,
    "image": "https://media-www.canadiantire.ca/product/fixing/electrical/rough-electrical/0522739/classic-oversized-white-rocker-8c410613-9044-4f1f-916d-806c67da3b16-jpgrendition.jpg?im=whresize&wid=200&hei=200",
    "image_url": "https://media-www.canadiantire.ca/product/fixing/electrical/rough-electrical/0522739/classic-oversized-white-rocker-8c410613-9044-4f1f-916d-806c67da3b16-jpgrendition.jpg?im=whresize&wid=200&hei=200",
    "url": "https://www.canadiantire.ca/fr/pdp/plaque-d-interrupteur-a-bascule-surdimensionnee-atron-electro-industries-1037r-1-dispositif-blanc-0522739p.html",
    "link": "https://www.canadiantire.ca/fr/pdp/plaque-d-interrupteur-a-bascule-surdimensionnee-atron-electro-industries-1037r-1-dispositif-blanc-0522739p.html",
    "product_id": null,
    "sku": "0522739",
    "sku_formatted": "052-2739-8",
    "availability": "Il n’en reste que 1 #052-2739-8",
    "badges": [
      "Liquidation◊"
    ],
    "discount_percent": 64.16,
    "liquidation_price": 1.43,
    "liquidation_price_raw": "1,43 $",
    "sale_price": 1.43,
    "sale_price_raw": "1,43 $",
    "regular_price": 3.99,
    "regular_price_raw": "Était±  3,99 $prix était 3,99 $",
    "price_sale_clean": "1,43",
    "price_original_clean": "3,99"
  },
  {
    "store_id": "42",
    "city": "Guelph Stone Rd, ON",
    "name": "Lampe de poche et lampe frontale 3-en-1 légère service intense Police Security MORF Removables, 300 lumens",
    "title": "Lampe de poche et lampe frontale 3-en-1 légère service intense Police Security MORF Removables, 300 lumens",
    "price": 19.98,
    "price_raw": "19,98 $",
    "liquidation": true,
    "image": "https://media-www.canadiantire.ca/product/fixing/hardware/household-flashlights/0651765/police-security-morf-removables-3-in-1-headlamp-300-lumen-054d89ad-8b57-469e-89cd-70c4d72ae1fc-jpgrendition.jpg?im=whresize&wid=200&hei=200",
    "image_url": "https://media-www.canadiantire.ca/product/fixing/hardware/household-flashlights/0651765/police-security-morf-removables-3-in-1-headlamp-300-lumen-054d89ad-8b57-469e-89cd-70c4d72ae1fc-jpgrendition.jpg?im=whresize&wid=200&hei=200",
    "url": "https://www.canadiantire.ca/fr/pdp/lampe-de-poche-et-lampe-frontale-3-en-1-legere-service-intense-police-security-morf-removables-300-lumens-0651765p.html",
    "link": "https://www.canadiantire.ca/fr/pdp/lampe-de-poche-et-lampe-frontale-3-en-1-legere-service-intense-police-security-morf-removables-300-lumens-0651765p.html",
    "product_id": null,
    "sku": "0651765",
    "sku_formatted": "065-1765-0",
    "availability": "11 En Stock#065-1765-0",
    "badges": [
      "Liquidation◊Exclusivité"
    ],
    "discount_percent": 50.04,
    "liquidation_price": 19.98,
    "liquidation_price_raw": "19,98 $",
    "sale_price": 19.98,
    "sale_price_raw": "19,98 $",
    "regular_price": 39.99,
    "regular_price_raw": "Était±  39,99 $prix était 39,99 $",
    "price_sale_clean": "19,98",
    "price_original_clean": "39,99"
  },
  {
    "store_id": "42",
    "city": "Guelph Stone Rd, ON",
    "name": "Centres de table pour fête 1er anniversaire, bleu/doré",
    "title": "Centres de table pour fête 1er anniversaire, bleu/doré",
    "price": 1.93,
    "price_raw": "1,93 $",
    "liquidation": true,
    "image": "https://media-www.canadiantire.ca/product/seasonal-gardening/party-city-everyday/party-city-kids-birthday-pinatas/8543268/general-1st-birthday-blue-high-chair-decoration-3cc173fc-64c1-4b0f-803c-7af507b636f7-jpgrendition.jpg?im=whresize&wid=200&hei=200",
    "image_url": "https://media-www.canadiantire.ca/product/seasonal-gardening/party-city-everyday/party-city-kids-birthday-pinatas/8543268/general-1st-birthday-blue-high-chair-decoration-3cc173fc-64c1-4b0f-803c-7af507b636f7-jpgrendition.jpg?im=whresize&wid=200&hei=200",
    "url": "https://www.canadiantire.ca/fr/pdp/centres-de-table-pour-fete-1er-anniversaire-bleu-dore-8538644p.html",
    "link": "https://www.canadiantire.ca/fr/pdp/centres-de-table-pour-fete-1er-anniversaire-bleu-dore-8538644p.html",
    "product_id": null,
    "sku": "8538644",
    "sku_formatted": "853-8644-0",
    "availability": "Il n’en reste que 2 #853-8644-0",
    "badges": [
      "Liquidation◊"
    ],
    "discount_percent": 75.84,
    "liquidation_price": 1.93,
    "liquidation_price_raw": "1,93 $",
    "sale_price": 1.93,
    "sale_price_raw": "1,93 $",
    "regular_price": 7.99,
    "regular_price_raw": "Était±  7,99 $prix était 7,99 $",
    "price_sale_clean": "1,93",
    "price_original_clean": "7,99"
  },
  {
    "store_id": "42",
    "city": "Guelph Stone Rd, ON",
    "name": "Bobine de rechange pour coupe-herbe à tige Greenworks, 60 V, à double fil",
    "title": "Bobine de rechange pour coupe-herbe à tige Greenworks, 60 V, à double fil",
    "price": 11.93,
    "price_raw": "11,93 $",
    "liquidation": true,
    "image": "https://media-www.canadiantire.ca/product/seasonal-gardening/outdoor-tools/ope-parts-accessories/0601578/greenworks-60v-gen-ii-spool-head-assembly-b87d502d-518b-45ed-a9a6-d22a35cdea2f-jpgrendition.jpg?im=whresize&wid=200&hei=200",
    "image_url": "https://media-www.canadiantire.ca/product/seasonal-gardening/outdoor-tools/ope-parts-accessories/0601578/greenworks-60v-gen-ii-spool-head-assembly-b87d502d-518b-45ed-a9a6-d22a35cdea2f-jpgrendition.jpg?im=whresize&wid=200&hei=200",
    "url": "https://www.canadiantire.ca/fr/pdp/bobine-de-rechange-pour-coupe-herbe-a-tige-greenworks-60-v-a-double-fil-0601578p.html",
    "link": "https://www.canadiantire.ca/fr/pdp/bobine-de-rechange-pour-coupe-herbe-a-tige-greenworks-60-v-a-double-fil-0601578p.html",
    "product_id": null,
    "sku": "0601578",
    "sku_formatted": "060-1578-6",
    "availability": "Il n’en reste que 1 #060-1578-6",
    "badges": [
      "Liquidation◊"
    ],
    "discount_percent": 60.22,
    "liquidation_price": 11.93,
    "liquidation_price_raw": "11,93 $",
    "sale_price": 11.93,
    "sale_price_raw": "11,93 $",
    "regular_price": 29.99,
    "regular_price_raw": "Était±  29,99 $prix était 29,99 $",
    "price_sale_clean": "11,93",
    "price_original_clean": "29,99"
  },
  {
    "store_id": "42",
    "city": "Guelph Stone Rd, ON",
    "name": "Costume d'Halloween, robe de sorcière lumineuse rose/violet avec chapeau, enfant et toute petite, choix de tailles",
    "title": "Costume d'Halloween, robe de sorcière lumineuse rose/violet avec chapeau, enfant et toute petite, choix de tailles",
    "price": 24.99,
    "price_raw": "24,99 $",
    "liquidation": true,
    "image": "https://media-www.canadiantire.ca/product/automotive/party-city-seasonal/party-city-halloween-costumes/8519282/453-child-light-up-sparkle-witch-costume-td-3-4--233644cb-25f0-4d5a-8e07-ff56e2b5f46d-jpgrendition.jpg?im=whresize&wid=200&hei=200",
    "image_url": "https://media-www.canadiantire.ca/product/automotive/party-city-seasonal/party-city-halloween-costumes/8519282/453-child-light-up-sparkle-witch-costume-td-3-4--233644cb-25f0-4d5a-8e07-ff56e2b5f46d-jpgrendition.jpg?im=whresize&wid=200&hei=200",
    "url": "https://www.canadiantire.ca/fr/pdp/costume-d-halloween-robe-de-sorciere-lumineuse-rose-violet-avec-chapeau-enfant-et-toute-petite-choix-de-tailles-8519282p.html",
    "link": "https://www.canadiantire.ca/fr/pdp/costume-d-halloween-robe-de-sorciere-lumineuse-rose-violet-avec-chapeau-enfant-et-toute-petite-choix-de-tailles-8519282p.html",
    "product_id": null,
    "sku": "8519282",
    "sku_formatted": "851-9282",
    "availability": null,
    "badges": [
      "Liquidation◊"
    ],
    "discount_percent": 50.01,
    "liquidation_price": 24.99,
    "liquidation_price_raw": "24,99 $",
    "sale_price": 24.99,
    "sale_price_raw": "24,99 $",
    "regular_price": 49.99,
    "regular_price_raw": "49,99 $Était   et+ prix était à partir de 49,99 $",
    "price_sale_clean": "24,99",
    "price_original_clean": "49,99"
  },
  {
    "store_id": "42",
    "city": "Guelph Stone Rd, ON",
    "name": "Collier pour animal de compagnie Perri's, motif guépard",
    "title": "Collier pour animal de compagnie Perri's, motif guépard",
    "price": 3.93,
    "price_raw": "3,93 $",
    "liquidation": true,
    "image": "https://media-www.canadiantire.ca/product/living/pet-care/pet-accessories/1427573/perri-s-pet-collar-cheetah-small-05b8926d-32df-4b25-aa88-c0d02a982350-jpgrendition.jpg?im=whresize&wid=200&hei=200",
    "image_url": "https://media-www.canadiantire.ca/product/living/pet-care/pet-accessories/1427573/perri-s-pet-collar-cheetah-small-05b8926d-32df-4b25-aa88-c0d02a982350-jpgrendition.jpg?im=whresize&wid=200&hei=200",
    "url": "https://www.canadiantire.ca/fr/pdp/collier-pour-animal-de-compagnie-perri-s-motif-guepard-1427573p.html",
    "link": "https://www.canadiantire.ca/fr/pdp/collier-pour-animal-de-compagnie-perri-s-motif-guepard-1427573p.html",
    "product_id": null,
    "sku": "1427573",
    "sku_formatted": "142-7573",
    "availability": null,
    "badges": [
      "Liquidation◊Exclusivité"
    ],
    "discount_percent": 73.78,
    "liquidation_price": 3.93,
    "liquidation_price_raw": "3,93 $",
    "sale_price": 3.93,
    "sale_price_raw": "3,93 $",
    "regular_price": 14.99,
    "regular_price_raw": "14,99 $Était   et+ prix était à partir de 14,99 $",
    "price_sale_clean": "3,93",
    "price_original_clean": "14,99"
  }
]
